{
  "project_info": {
    "project_number": "696353067914",
    "firebase_url": "https://minimarket-9bc34.firebaseio.com",
    "project_id": "minimarket-9bc34",
    "storage_bucket": "minimarket-9bc34.appspot.com"
  },
  "client": [
    {
      "client_info": {
        "mobilesdk_app_id": "1:696353067914:android:c2ba0b0263ac99a2",
        "android_client_info": {
          "package_name": "com.balinasoft.minimarket"
        }
      },
      "oauth_client": [
        {
          "client_id": "696353067914-eqcqjovlbofqoitucjj8v71roanfbjd0.apps.googleusercontent.com",
          "client_type": 3
        }
      ],
      "api_key": [
        {
          "current_key": "AIzaSyCiI7leNRr7MX-oEXX_ZSrzip1a9vSBXh4"
        }
      ],
      "services": {
        "analytics_service": {
          "status": 1
        },
        "appinvite_service": {
          "status": 1,
          "other_platform_oauth_client": []
        },
        "ads_service": {
          "status": 2
        }
      }
    }
  ],
  "configuration_version": "1"
}